aatools/__init__.py
aatools/_modidx.py
aatools/core.py
aatools/datasets.py
aatools/eda.py
aatools/model_evaluation.py
aatools-0.0.2.dist-info/LICENSE
aatools-0.0.2.dist-info/METADATA
aatools-0.0.2.dist-info/WHEEL
aatools-0.0.2.dist-info/entry_points.txt
aatools-0.0.2.dist-info/top_level.txt
aatools-0.0.2.dist-info/RECORD
